onorm/__init__.py
onorm/minmax.py
onorm/mvnorm.py
onorm/normalization_base.py
onorm/pipeline.py
onorm/quantile.py
onorm/standard.py
onorm/winsorize.py
onorm-0.3.0.dist-info/LICENSE
onorm-0.3.0.dist-info/METADATA
onorm-0.3.0.dist-info/WHEEL
onorm-0.3.0.dist-info/RECORD
