Metadata-Version: 2.3
Name: onorm
Version: 0.3.0
Summary: A library for normalizing streams of incoming data, particularly focused on improving sequential experimentation.
License: Apache-2.0
Keywords: normalization,standardization,online-learning,streaming-data,data-preprocessing
Author: Drew Dimmery
Author-email: pypi@ddimmery.com
Requires-Python: >=3.12,<4.0
Classifier: Development Status :: 4 - Beta
Classifier: Intended Audience :: Developers
Classifier: Intended Audience :: Science/Research
Classifier: License :: OSI Approved :: Apache Software License
Classifier: Programming Language :: Python :: 3
Classifier: Programming Language :: Python :: 3.12
Classifier: Programming Language :: Python :: 3.13
Classifier: Topic :: Scientific/Engineering
Classifier: Topic :: Scientific/Engineering :: Mathematics
Classifier: Topic :: Software Development :: Libraries
Classifier: Topic :: Software Development :: Libraries :: Python Modules
Classifier: Typing :: Typed
Requires-Dist: fastdigest (>=0.8,<0.9)
Requires-Dist: numpy (>=1.22)
Requires-Dist: scipy (>=1.16.2,<2.0.0)
Project-URL: Homepage, https://passexp.github.io/onorm/
Project-URL: Repository, https://github.com/passexp/onorm
